kestrelgrid/__init__.py
kestrelgrid/raw_reader/__init__.py
kestrelgrid/raw_reader/raw_reader.py
kestrelgrid/raw_reader/types.py
kestrelgrid-0.1.0.dist-info/LICENSE
kestrelgrid-0.1.0.dist-info/METADATA
kestrelgrid-0.1.0.dist-info/WHEEL
kestrelgrid-0.1.0.dist-info/RECORD
