Metadata-Version: 2.3
Name: kestrelgrid
Version: 0.1.0
Summary: 
Author: David Daigle
Author-email: ddaigle@daiglegrid.com
Requires-Python: >=3.9,<4.0
Classifier: Programming Language :: Python :: 3
Classifier: Programming Language :: Python :: 3.9
Classifier: Programming Language :: Python :: 3.10
Classifier: Programming Language :: Python :: 3.11
Classifier: Programming Language :: Python :: 3.12
Classifier: Programming Language :: Python :: 3.13
Requires-Dist: numpy
Requires-Dist: pytz
